[{"id":1,"title_name":"角色等级达到","title_name_language":11055,"typ":1},{"id":2,"title_name":"总战力达到","title_name_language":11056,"typ":1},{"id":3,"title_name":"打造出升华及以上品质装备","title_name_language":11057,"typ":1},{"id":4,"title_name":"获得装备","title_name_language":11058,"typ":1},{"id":15,"title_name":"解锁英雄【埃尔蒂】","title_name_language":61094,"typ":1},{"id":16,"title_name":"解锁英雄【忒瑞丝】","title_name_language":61095,"typ":1},{"id":17,"title_name":"解锁英雄【安德瑞丝】","title_name_language":61096,"typ":1},{"id":18,"title_name":"获得永久时装【恐虐之刃】","title_name_language":61097,"typ":1},{"id":19,"title_name":"获得永久时装【吸血鬼猎人】","title_name_language":61098,"typ":1},{"id":20,"title_name":"获得永久时装【审判之矢】","title_name_language":61099,"typ":1},{"id":21,"title_name":"获得永久时装【猩红女王】","title_name_language":61100,"typ":1},{"id":22,"title_name":"获得永久时装【幽邃女爵】","title_name_language":61101,"typ":1},{"id":5,"title_name":"强化结晶消耗","title_name_language":11059,"typ":2},{"id":6,"title_name":"秘火晶簇消耗","title_name_language":11060,"typ":2},{"id":7,"title_name":"装备附魔次数","title_name_language":11061,"typ":2},{"id":8,"title_name":"逸闻探索次数","title_name_language":11062,"typ":3},{"id":9,"title_name":"位面寻宝次数","title_name_language":11063,"typ":3},{"id":10,"title_name":"远征次数","title_name_language":11064,"typ":3},{"id":11,"title_name":"魂契总等级","title_name_language":11065,"typ":3},{"id":12,"title_name":"收集遗物","title_name_language":11066,"typ":4},{"id":13,"title_name":"遗物总星级","title_name_language":11067,"typ":4},{"id":14,"title_name":"遗物淬炼总等级","title_name_language":11068,"typ":4}]