[{"chest_img":"img_guanka_lock01","game_time":15,"holen_num":3,"id":1,"name":"开锁","position":[[800,3300],[4500,6000],[7500,9000]],"spacing":9000,"speed_ball":[40000,30000,25000],"speed_ball_last":[60000,50000,40000]},{"chest_img":"img_guanka_lock01","game_time":12,"holen_num":4,"id":2,"name":"开锁","position":[[800,2400],[3500,4500],[5500,7000],[7500,9200]],"spacing":9000,"speed_ball":[40000,30000,25000,20000],"speed_ball_last":[60000,50000,40000,30000]},{"chest_img":"img_guanka_lock01","game_time":10,"holen_num":5,"id":3,"name":"开锁","position":[[800,1800],[2200,3800],[4200,5800],[6200,7800],[8200,9400]],"spacing":9000,"speed_ball":[40000,30000,25000,20000,20000],"speed_ball_last":[60000,50000,40000,30000,30000]}]